davisinteractive/__init__.py
davisinteractive/common.py
davisinteractive/logging.py
davisinteractive/connector/__init__.py
davisinteractive/connector/abstract.py
davisinteractive/connector/fabric.py
davisinteractive/connector/local.py
davisinteractive/connector/remote.py
davisinteractive/dataset/__init__.py
davisinteractive/dataset/davis.json
davisinteractive/dataset/davis.py
davisinteractive/dataset/davis_test.py
davisinteractive/evaluation/__init__.py
davisinteractive/evaluation/service.py
davisinteractive/evaluation/service_test.py
davisinteractive/metrics/__init__.py
davisinteractive/metrics/jaccard.py
davisinteractive/metrics/jaccard_test.py
davisinteractive/robot/__init__.py
davisinteractive/robot/interactive_robot.py
davisinteractive/robot/interactive_robot_test.py
davisinteractive/session/__init__.py
davisinteractive/session/session.py
davisinteractive/session/session_test.py
davisinteractive/utils/__init__.py
davisinteractive/utils/mask.py
davisinteractive/utils/mask_test.py
davisinteractive/utils/operations.py
davisinteractive/utils/scribbles.py
davisinteractive/utils/scribbles_test.py
davisinteractive/utils/visualization.py
davisinteractive-0.0.5.dist-info/DESCRIPTION.rst
davisinteractive-0.0.5.dist-info/METADATA
davisinteractive-0.0.5.dist-info/RECORD
davisinteractive-0.0.5.dist-info/WHEEL
davisinteractive-0.0.5.dist-info/metadata.json
davisinteractive-0.0.5.dist-info/top_level.txt
davisinteractive-0.0.5.dist-info/zip-safe
