Metadata-Version: 2.0
Name: davisinteractive
Version: 0.0.5
Summary: Evaluation Framework for DAVIS Interactive Segmentation
Home-page: https://github.com/albertomontesg/davis-interactive
Author: Alberto Montes
Author-email: al.montes.gomez@gmail.com
License: GPL v3
Keywords: segmentation
Platform: UNKNOWN
Classifier: Development Status :: 2 - Pre-Alpha
Classifier: Intended Audience :: Developers
Classifier: Intended Audience :: Education
Classifier: Intended Audience :: Science/Research
Classifier: License :: OSI Approved :: GNU General Public License v3 (GPLv3)
Classifier: Programming Language :: Python :: 2
Classifier: Programming Language :: Python :: 2.7
Classifier: Programming Language :: Python :: 3
Classifier: Programming Language :: Python :: 3.5
Classifier: Programming Language :: Python :: 3.6
Classifier: Topic :: Scientific/Engineering :: Human Machine Interfaces
Classifier: Topic :: Software Development :: Libraries
Classifier: Topic :: Software Development :: Libraries :: Python Modules
Requires-Python: >=2.7, !=3.0.*, !=3.1.*, !=3.2.*, !=3.3.*, <4
Requires-Dist: numpy (>=1.12.1)
Requires-Dist: scikit-learn (>=0.18)
Requires-Dist: scikit-image (>=0.13.1)
Requires-Dist: networkx (>=2.0)
Requires-Dist: scipy (>=1.0.0)
Requires-Dist: pandas (>=0.21.1)
Requires-Dist: absl-py (>=0.1.13)
Requires-Dist: Pillow (>=4.1.1)
Requires-Dist: six (>=1.10.0)
Requires-Dist: mock; python_version < "3.0"
Requires-Dist: pathlib2; python_version < "3.5"
